__init__.py
rmvenv.py
rmvenv-0.2.0.dist-info/licenses/LICENSE.txt
rmvenv-0.2.0.dist-info/METADATA
rmvenv-0.2.0.dist-info/WHEEL
rmvenv-0.2.0.dist-info/entry_points.txt
rmvenv-0.2.0.dist-info/top_level.txt
rmvenv-0.2.0.dist-info/RECORD
