Metadata-Version: 2.4
Name: rmvenv
Version: 0.2.0
Summary: Find and delete built environments
Author-email: Daisy F <daisyfarns@gmail.com>
License: MIT License
Project-URL: Homepage, https://github.com/DaisyFarns/rmvenv
Keywords: venv,delete,manage,list,rust,target
Classifier: Programming Language :: Python :: 3
Classifier: License :: OSI Approved :: MIT License
Classifier: Development Status :: 4 - Beta
Classifier: Intended Audience :: Developers
Classifier: Intended Audience :: End Users/Desktop
Classifier: Natural Language :: English
Classifier: Operating System :: OS Independent
Classifier: Topic :: Software Development :: Build Tools
Classifier: Topic :: System :: Archiving
Requires-Python: >=3.10
License-File: LICENSE.txt
Dynamic: license-file
